paginator/__init__.py
paginator/objects.py
paginator/paginator.py
paginator.py-0.9.4.dist-info/LICENSE
paginator.py-0.9.4.dist-info/METADATA
paginator.py-0.9.4.dist-info/WHEEL
paginator.py-0.9.4.dist-info/top_level.txt
paginator.py-0.9.4.dist-info/RECORD
