Metadata-Version: 2.1
Name: paginator.py
Version: 0.9.4
Summary: Simple to use discord paginator for messages and embeds with reactions and buttons.
Home-page: https://github.com/FlamptX/paginator.py
Author: Flampt
License: MIT
Project-URL: Source, https://github.com/FlamptX/paginator.py
Project-URL: Documentation, https://flampt.gitbook.io/paginator
Keywords: discord paginator discord-paginator
Classifier: Programming Language :: Python :: 3
Classifier: License :: OSI Approved :: MIT License
Requires-Python: >=3.6
License-File: LICENSE
Requires-Dist: discord.py
Requires-Dist: asyncio
